quilt3_local/__init__.py
quilt3_local/api.py
quilt3_local/async_cache.py
quilt3_local/aws.py
quilt3_local/buckets.py
quilt3_local/catalog_bundle/0108e89c9003e8c14ea3c4e99b09653e.woff
quilt3_local/catalog_bundle/02271ec5cb9f5b4588ac53d7efbe6de8.woff
quilt3_local/catalog_bundle/05726d34da786f58b91671fd9618f4f3.png
quilt3_local/catalog_bundle/073b3402d036714b43709614d1da717a.woff
quilt3_local/catalog_bundle/07f172de9a3a1ff2cd219b43bd4bdff1.jpeg
quilt3_local/catalog_bundle/0b0421a0440c7b186aa9ff21e28e0842.png
quilt3_local/catalog_bundle/0c3b8929d377c0e9b2f3a9c872e3337b.woff
quilt3_local/catalog_bundle/1000.6b28a77c846c9c4fbfe8.chunk.js
quilt3_local/catalog_bundle/1000.6b28a77c846c9c4fbfe8.chunk.js.gz
quilt3_local/catalog_bundle/1000.6b28a77c846c9c4fbfe8.chunk.js.map
quilt3_local/catalog_bundle/1149.f8d2e8a039c1efab531d.chunk.js
quilt3_local/catalog_bundle/1149.f8d2e8a039c1efab531d.chunk.js.map
quilt3_local/catalog_bundle/1183.22180fcf696b8da0dbe3.chunk.js
quilt3_local/catalog_bundle/1183.22180fcf696b8da0dbe3.chunk.js.map
quilt3_local/catalog_bundle/1198.46a7f0c33ced5308f014.chunk.js
quilt3_local/catalog_bundle/1198.46a7f0c33ced5308f014.chunk.js.gz
quilt3_local/catalog_bundle/1198.46a7f0c33ced5308f014.chunk.js.map
quilt3_local/catalog_bundle/1214.201b0aa7abb82337c54d.chunk.js
quilt3_local/catalog_bundle/1214.201b0aa7abb82337c54d.chunk.js.gz
quilt3_local/catalog_bundle/1214.201b0aa7abb82337c54d.chunk.js.map
quilt3_local/catalog_bundle/121abb140e13c5b9bf43db5636b787a0.png
quilt3_local/catalog_bundle/1221.b2bc04e225dd3b25365a.chunk.js
quilt3_local/catalog_bundle/1221.b2bc04e225dd3b25365a.chunk.js.gz
quilt3_local/catalog_bundle/1221.b2bc04e225dd3b25365a.chunk.js.map
quilt3_local/catalog_bundle/1225.51c1f1f61e4e23343d38.chunk.js
quilt3_local/catalog_bundle/1225.51c1f1f61e4e23343d38.chunk.js.map
quilt3_local/catalog_bundle/1258.862851bbcda503d9bbe3.chunk.js
quilt3_local/catalog_bundle/1258.862851bbcda503d9bbe3.chunk.js.gz
quilt3_local-2.0.0.dist-info/METADATA
quilt3_local-2.0.0.dist-info/WHEEL
quilt3_local-2.0.0.dist-info/entry_points.txt
quilt3_local-2.0.0.dist-info/RECORD
