Metadata-Version: 2.1
Name: quilt3_local
Version: 2.0.0
Summary: Quilt3 catalog: local development mode
Home-page: https://quiltdata.com
License: Apache-2.0
Author: quiltdata
Author-email: contact@quiltdata.io
Requires-Python: >=3.9,<3.12
Classifier: License :: OSI Approved :: Apache Software License
Classifier: Programming Language :: Python :: 3
Classifier: Programming Language :: Python :: 3.9
Classifier: Programming Language :: Python :: 3.10
Classifier: Programming Language :: Python :: 3.11
Requires-Dist: Pillow (>=8.4,<10.0)
Requires-Dist: aicsimageio (>=3.1.4,<3.2.0)
Requires-Dist: aiobotocore[boto3] (>=2.1.0,<3.0.0)
Requires-Dist: aiohttp (>=3.8.1,<4.0.0)
Requires-Dist: ariadne (>=0.14.1,<0.25)
Requires-Dist: cachetools (>=5.0.0,<6.0.0)
Requires-Dist: fastapi (>=0.70.0,<0.116.0)
Requires-Dist: fcsparser (>=0.2.4,<0.3.0)
Requires-Dist: fsspec[http] (>=2022.1.0)
Requires-Dist: imageio (>=2.5.0,<2.6.0)
Requires-Dist: importlib-resources (>=5.3.0,<6.0.0)
Requires-Dist: jsonschema (>=3.0.1,<4.0.0)
Requires-Dist: nbconvert (>=6.3.0,<7.0.0)
Requires-Dist: nbformat (>=5.1.3,<6.0.0)
Requires-Dist: numpy (>=1.21.4,<2.0.0) ; python_version < "3.11"
Requires-Dist: numpy (>=1.23.2,<2.0.0) ; python_version >= "3.11"
Requires-Dist: openpyxl (>=3.0.9,<4.0.0)
Requires-Dist: pandas (>=1.3.4,<2.0.0) ; python_version < "3.11"
Requires-Dist: pandas (>=1.5.0,<2.0.0) ; python_version >= "3.11"
Requires-Dist: psutil (>=5.8.0,<6.0.0)
Requires-Dist: pyarrow (>=7,<13)
Requires-Dist: requests (>=2.26.0,<3.0.0)
Requires-Dist: starlette (>=0.17)
Requires-Dist: xlrd (>=2.0.1,<3.0.0)
Project-URL: Documentation, https://docs.quiltdata.com
Project-URL: Repository, https://github.com/quiltdata/local
